aiofile/__init__.py
aiofile/aio.py
aiofile/py.typed
aiofile/utils.py
aiofile/version.py
aiofile-3.8.8.dist-info/LICENCE
aiofile-3.8.8.dist-info/LICENCE.md
aiofile-3.8.8.dist-info/METADATA
aiofile-3.8.8.dist-info/WHEEL
aiofile-3.8.8.dist-info/top_level.txt
aiofile-3.8.8.dist-info/RECORD
