Metadata-Version: 2.1
Name: aiofile
Version: 3.8.8
Summary: Asynchronous file operations.
Home-page: http://github.com/mosquito/aiofile
Author: Dmitry Orlov <me@mosquito.su>
Author-email: me@mosquito.su
License: Apache 2
Keywords: aio,python,asyncio,fileio,io
Platform: POSIX
Classifier: Development Status :: 5 - Production/Stable
Classifier: Environment :: Console
Classifier: Intended Audience :: Developers
Classifier: Intended Audience :: Education
Classifier: Intended Audience :: End Users/Desktop
Classifier: License :: OSI Approved :: Apache Software License
Classifier: Natural Language :: English
Classifier: Natural Language :: Russian
Classifier: Operating System :: POSIX :: Linux
Classifier: Operating System :: MacOS :: MacOS X
Classifier: Programming Language :: Python
Classifier: Programming Language :: Python :: 3 :: Only
Classifier: Programming Language :: Python :: 3.7
Classifier: Programming Language :: Python :: 3.8
Classifier: Programming Language :: Python :: 3.9
Classifier: Programming Language :: Python :: 3.10
Classifier: Programming Language :: Python :: 3.11
Classifier: Programming Language :: Python :: Implementation :: CPython
Classifier: Topic :: Software Development :: Libraries
Classifier: Topic :: System
Classifier: Topic :: System :: Operating System
Provides: aiofile
Requires-Python: >=3.7, <4
Provides-Extra: develop
License-File: LICENCE
License-File: LICENCE.md
